roseng/__init__.py
roseng/behavior.py
roseng/device.py
roseng/engine.py
roseng/pin.py
roseng/protocol.py
roseng/util.py
roseng-0.5.dist-info/DESCRIPTION.rst
roseng-0.5.dist-info/METADATA
roseng-0.5.dist-info/RECORD
roseng-0.5.dist-info/WHEEL
roseng-0.5.dist-info/metadata.json
roseng-0.5.dist-info/top_level.txt
