Metadata-Version: 2.0
Name: roseng
Version: 0.5
Summary: ROS Engine
Home-page: UNKNOWN
Author: Dirk Zhou
Author-email: dontbmh2011@gmail.com
License: MIT
Platform: UNKNOWN
Requires-Python: >=3.6
